replifactory/__init__.py
replifactory/culture/__init__.py
replifactory/culture/batch.py
replifactory/culture/blank.py
replifactory/culture/chemostat.py
replifactory/culture/culture_functions.py
replifactory/culture/culture_universal.py
replifactory/culture/custom_culture_1.py
replifactory/culture/lagoon.py
replifactory/culture/lagoon_seva.py
replifactory/culture/morbidostat.py
replifactory/culture/patients.py
replifactory/culture/plotting.py
replifactory/culture/stress_ramp.py
replifactory/culture/turbidostat.py
replifactory/device/__init__.py
replifactory/device/adc.py
replifactory/device/base_device.py
replifactory/device/calibration.py
replifactory/device/cleaning.py
replifactory/device/dilution.py
replifactory/device/eeprom.py
replifactory/device/lasers.py
replifactory/device/morbidostat_device.py
replifactory/device/od_sensor.py
replifactory/device/pump.py
replifactory/device/pwm.py
replifactory/device/stepper.py
replifactory/device/stirrers.py
replifactory/device/test_hardware.py
replifactory/device/thermometers.py
replifactory/device/valves.py
replifactory/device/workers.py
replifactory/GUI/__init__.py
replifactory/GUI/calibration_widgets.py
replifactory/GUI/camera_widgets.py
replifactory/GUI/device_control_widgets.py
replifactory/GUI/device_tab.py
replifactory/GUI/experiment_program_tab.py
replifactory/GUI/graph_tab.py
replifactory/GUI/hardware_testing_widgets.py
replifactory/GUI/main_gui.py
replifactory/GUI/notifier.py
replifactory/GUI/preparation_tab.py
replifactory/GUI/run_tab.py
replifactory/GUI/setup_menu.py
replifactory/GUI/status_tab.py
replifactory/GUI/telegram_bot.py
replifactory/GUI/universal_culture_gui.py
replifactory/status/__init__.py
replifactory/test/__init__.py
replifactory/test/test_culture_universal.py
replifactory/util/__init__.py
replifactory/util/custom_plots.py
replifactory/util/experiment.py
replifactory/util/growth_rate.py
replifactory/util/loading.py
replifactory/util/other.py
replifactory-0.0.61.dist-info/METADATA
replifactory-0.0.61.dist-info/WHEEL
replifactory-0.0.61.dist-info/RECORD
