Metadata-Version: 2.1
Name: replifactory
Version: 0.0.61
Summary: replifactory morbidostat python package
Home-page: https://replifactory.com
Author: Catalin Rusnac
Author-email: ctlnrsnc@gmail.com
Maintainer: Fedor Gagarin
Maintainer-email: fddgagarin@gmail.com
Requires-Python: >=3.9,<4.0
Classifier: Programming Language :: Python :: 3
Classifier: Programming Language :: Python :: 3.9
Classifier: Programming Language :: Python :: 3.10
Classifier: Programming Language :: Python :: 3.11
Requires-Dist: PyYAML (>=6.0,<7.0)
Requires-Dist: ipython (>=7.29.0,<8.0.0)
Requires-Dist: ipywidgets (>=7.5.1,<8.0.0)
Requires-Dist: jupyter (>=1.0.0,<2.0.0)
Requires-Dist: matplotlib (>=3.3.0,<4.0.0)
Requires-Dist: numpy (>=1.20.2,<2.0.0)
Requires-Dist: pandas (>=1.1.0,<2.0.0)
Requires-Dist: pyftdi (>=0.52.9,<0.53.0)
Requires-Dist: python-telegram-bot (>=20.0,<21.0)
Requires-Dist: schedule (>=0.6.0,<0.7.0)
Requires-Dist: scipy (>=1.6.3,<2.0.0)
